Spectra3D/__init__.py
spectra3D-0.0.1.3.2.dist-info/LICENSE
spectra3D-0.0.1.3.2.dist-info/METADATA
spectra3D-0.0.1.3.2.dist-info/WHEEL
spectra3D-0.0.1.3.2.dist-info/top_level.txt
spectra3D-0.0.1.3.2.dist-info/RECORD
