Metadata-Version: 2.1
Name: spectra3D
Version: 0.0.1.3.2
Summary: Adding spectrum data to 3D
Home-page: https://github.com/i3drobotics/Spectra3D
Author: Ben Knight
Author-email: bknight@i3drobotics.com
License: UNKNOWN
Platform: UNKNOWN
Classifier: Programming Language :: Python :: 3
Classifier: License :: OSI Approved :: MIT License
Classifier: Operating System :: OS Independent
Requires-Python: >=3.5
Requires-Dist: numpy
Requires-Dist: matplotlib
Requires-Dist: plyfile
